{
  "data": {
    "totalPages": 1,
    "page": 1,
    "content": [
      {
        "xmlName": "process_1611713350036",
        "createUserId": "1",
        "sendId": "2",
        "statusCN": "已启动",
        "num": 1,
        "endEventObj": {
          "title": "",
          "type": [],
          "users": [],
          "mes": ""
        },
        "version": 1,
        "createUserCN": "管理员",
        "des": "",
        "sendCN": "漏洞",
        "createTime": "2021-01-27 10:08:35",
        "xml": "<?xml version=\"1.0\" encoding=\"UTF-8\"?>\n<definitions xmlns=\"http://www.omg.org/spec/BPMN/20100524/MODEL\" xmlns:xsi=\"http://www.w3.org/2001/XMLSchema-instance\" xmlns:bpmndi=\"http://www.omg.org/spec/BPMN/20100524/DI\" xmlns:omgdc=\"http://www.omg.org/spec/DD/20100524/DC\" xmlns:camunda=\"http://camunda.org/schema/1.0/bpmn\" xmlns:di=\"http://www.omg.org/spec/DD/20100524/DI\" xmlns:xsd=\"http://www.w3.org/2001/XMLSchema\" xmlns:flowable=\"http://flowable.org/bpmn\" targetNamespace=\"http://www.flowable.org/processdef\">\n  <process id=\"process_1611713350036\" name=\"name_ep6b22mi\" isExecutable=\"true\">\n    <startEvent id=\"Event_0gly3pi\" name=\"开始\">\n      <outgoing>Flow_0ntqzcl</outgoing>\n    </startEvent>\n    <serviceTask id=\"Activity_1x82dil\" name=\"自动\" camunda:class=\"com.boot.base.common.util.workflow.CallExternalSystemDelegate\" camunda:taskType=\"3\" camunda:warn=\"\" camunda:usersName=\"[]\">\n      <documentation>{\"id\":\"Activity_1x82dil\",\"type\":3,\"des\":\"\",\"warn\":[]}</documentation>\n      <incoming>Flow_0ntqzcl</incoming>\n    </serviceTask>\n    <sequenceFlow id=\"Flow_0ntqzcl\" sourceRef=\"Event_0gly3pi\" targetRef=\"Activity_1x82dil\" />\n    <group id=\"Group_0mh6p36\" categoryValueRef=\"CategoryValue_1p7sxin\" />\n  </process>\n  <category id=\"Category_18p6x23\">\n    <categoryValue id=\"CategoryValue_1p7sxin\" />\n  </category>\n  <bpmndi:BPMNDiagram id=\"BPMNDiagram_flow\">\n    <bpmndi:BPMNPlane id=\"BPMNPlane_flow\" bpmnElement=\"process_1611713350036\">\n      <bpmndi:BPMNEdge id=\"Flow_0ntqzcl_di\" bpmnElement=\"Flow_0ntqzcl\">\n        <di:waypoint x=\"95\" y=\"90\" />\n        <di:waypoint x=\"95\" y=\"225\" />\n      </bpmndi:BPMNEdge>\n      <bpmndi:BPMNShape id=\"Event_0gly3pi_di\" bpmnElement=\"Event_0gly3pi\">\n        <omgdc:Bounds x=\"75\" y=\"50\" width=\"40\" height=\"40\" />\n        <bpmndi:BPMNLabel>\n          <omgdc:Bounds x=\"84\" y=\"26\" width=\"22\" height=\"14\" />\n        </bpmndi:BPMNLabel>\n      </bpmndi:BPMNShape>\n      <bpmndi:BPMNShape id=\"Activity_1x82dil_di\" bpmnElement=\"Activity_1x82dil\">\n        <omgdc:Bounds x=\"45\" y=\"225\" width=\"100\" height=\"50\" />\n      </bpmndi:BPMNShape>\n      <bpmndi:BPMNShape id=\"Group_0mh6p36_di\" bpmnElement=\"Group_0mh6p36\">\n        <omgdc:Bounds x=\"-70\" y=\"-10\" width=\"330\" height=\"430\" />\n      </bpmndi:BPMNShape>\n    </bpmndi:BPMNPlane>\n  </bpmndi:BPMNDiagram>\n</definitions>\n",
        "deploymentId": "8f8d326e-6044-11eb-b7a8-02429d5084e0",
        "startConditionObj": [
          {
            "and": [
              {
                "val": "",
                "condition": "",
                "field": ""
              }
            ]
          }
        ],
        "userIds": [
          {
            "name": "孙广",
            "userId": "ff8080816b3f260e016b3f5389330045"
          },
          {
            "name": "张先生",
            "userId": "402881f16bd05f8f016bd0601b680000"
          },
          {
            "name": "管理员",
            "userId": "1"
          }
        ],
        "name": "漏洞魔板",
        "id": "ff8080817714f7b00177419972c30019",
        "status": 1
      },
      {
        "xmlName": "process_1610199116476",
        "createUserId": "1",
        "sendId": "1",
        "statusCN": "已启动",
        "num": 0,
        "endEventObj": {
          "title": "test",
          "type": [
            "0",
            "1"
          ],
          "users": [
            {
              "ids": [
                "402881f16bd05f8f016bd0601b680000",
                "8a8be6ac711b790a01711c561968007f"
              ],
              "userType": "0"
            }
          ],
          "mes": "特色与<div><br></div>"
        },
        "version": 1,
        "createUserCN": "管理员",
        "des": "<p>工单描述</p>",
        "sendCN": "告警",
        "createTime": "2021-01-20 17:43:39",
        "xml": "<?xml version=\"1.0\" encoding=\"UTF-8\"?>\n<definitions xmlns=\"http://www.omg.org/spec/BPMN/20100524/MODEL\" xmlns:xsi=\"http://www.w3.org/2001/XMLSchema-instance\" xmlns:bpmndi=\"http://www.omg.org/spec/BPMN/20100524/DI\" xmlns:omgdc=\"http://www.omg.org/spec/DD/20100524/DC\" xmlns:camunda=\"http://camunda.org/schema/1.0/bpmn\" xmlns:di=\"http://www.omg.org/spec/DD/20100524/DI\" xmlns:xsd=\"http://www.w3.org/2001/XMLSchema\" xmlns:flowable=\"http://flowable.org/bpmn\" targetNamespace=\"http://www.flowable.org/processdef\">\n  <process id=\"process_1610199116476\" name=\"主流程\" isExecutable=\"true\">\n    <startEvent id=\"Event_0gly3pi\" name=\"开始\">\n      <outgoing>Flow_05w48v1</outgoing>\n    </startEvent>\n    <userTask id=\"Activity_0cptsx9\" name=\"分析\" camunda:candidateUsers=\"${Activity_0cptsx9_users}\" camunda:taskType=\"2\" camunda:approvalUsers=\"%5B%7B%22dealUserType%22:%222%22,%22users%22:%5B%7B%22type%22:%222%22,%22ids%22:%5B%224028a7d86b216c9e016b2187b1d70000%22%5D%7D%5D%7D%5D\" camunda:approvalUsersNames=\"%5B%7B%22dealUserTypeNmae%22:%22%E4%BA%BA%E5%91%98,%E9%83%A8%E9%97%A8,%E8%A7%92%E8%89%B2,%E7%94%A8%E6%88%B7%E7%BB%84%22,%22dealUserType%22:%222%22,%22_users%22:%5B%7B%22createTimeFormat%22:%222019-06-04%2016:07:49%22,%22createTime%22:%222019-06-04%2016:07:49%22,%22roleName%22:%22%E5%88%86%E6%9E%90%E7%A0%94%E5%88%A4%E7%BB%84%22,%22id%22:%224028a7d86b216c9e016b2187b1d70000%22,%22status%22:0,%22type%22:%222%22%7D%5D,%22users%22:%5B%7B%22type%22:%222%22,%22ids%22:%5B%224028a7d86b216c9e016b2187b1d70000%22%5D%7D%5D,%22userStr%22:%22%E5%88%86%E6%9E%90%E7%A0%94%E5%88%A4%E7%BB%84%22%7D%5D\" camunda:warn=\"%5B%5D\" camunda:usersName=\"%5B%5D\" camunda:dealType=\"0\" camunda:fieldsReal=\"%5B%7B%22field%22:%22reportName%22,%22name%22:%22%E5%91%8A%E8%AD%A6%E5%90%8D%E7%A7%B0%22,%22type%22:%221%22,%22isSelected%22:true%7D,%7B%22field%22:%22reportLevel%22,%22name%22:%22%E5%91%8A%E8%AD%A6%E7%AD%89%E7%BA%A7%22,%22type%22:%221%22,%22isSelected%22:true%7D,%7B%22field%22:%22analyzePro%22,%22name%22:%22%E5%88%86%E6%9E%90%E8%BF%87%E7%A8%8B%22,%22type%22:%221%22,%22isSelected%22:true%7D,%7B%22field%22:%22disposalAdvise%22,%22name%22:%22%E5%A4%84%E7%BD%AE%E5%BB%BA%E8%AE%AE%22,%22type%22:%221%22,%22isSelected%22:true%7D%5D\">\n      <documentation>{\"id\":\"Activity_0cptsx9\",\"type\":2,\"des\":\"\",\"users\":[{\"dealUserType\":\"2\",\"users\":[{\"type\":\"2\",\"ids\":[\"4028a7d86b216c9e016b2187b1d70000\"]}]}],\"waitTime\":\"\",\"waitTimeType\":\"\",\"warn\":[],\"dealType\":\"0\",\"fields\":[{\"field\":\"reportName\",\"name\":\"告警名称\",\"type\":\"1\"},{\"field\":\"reportLevel\",\"name\":\"告警等级\",\"type\":\"1\"},{\"field\":\"analyzePro\",\"name\":\"分析过程\",\"type\":\"1\"},{\"field\":\"disposalAdvise\",\"name\":\"处置建议\",\"type\":\"1\"}]}</documentation>\n      <extensionElements>\n        <camunda:taskListener class=\"com.boot.base.common.util.workflow.TaskCreateListener\" event=\"create\" />\n        <camunda:taskListener class=\"com.boot.base.common.util.workflow.TaskCompleteListener\" event=\"complete\" />\n      </extensionElements>\n      <incoming>Flow_05w48v1</incoming>\n      <outgoing>Flow_0ef2tb0</outgoing>\n      <outgoing>Flow_0kofjgf</outgoing>\n    </userTask>\n    <sequenceFlow id=\"Flow_05w48v1\" sourceRef=\"Event_0gly3pi\" targetRef=\"Activity_0cptsx9\" />\n    <userTask id=\"Activity_166ukp1\" name=\"溯源\" camunda:candidateUsers=\"${Activity_166ukp1_users}\" camunda:taskType=\"2\" camunda:approvalUsers=\"%5B%7B%22dealUserType%22:%222%22,%22users%22:%5B%7B%22type%22:%222%22,%22ids%22:%5B%228a8b71a776e29a320176e5c91c9601fd%22%5D%7D%5D%7D%5D\" camunda:approvalUsersNames=\"%5B%7B%22dealUserTypeNmae%22:%22%E4%BA%BA%E5%91%98,%E9%83%A8%E9%97%A8,%E8%A7%92%E8%89%B2,%E7%94%A8%E6%88%B7%E7%BB%84%22,%22dealUserType%22:%222%22,%22_users%22:%5B%7B%22createTimeFormat%22:%222021-01-09%2014:15:31%22,%22createTime%22:%222021-01-09%2014:15:31%22,%22roleName%22:%22%E6%BA%AF%E6%BA%90%E5%8F%96%E8%AF%81%E7%BB%84%22,%22id%22:%228a8b71a776e29a320176e5c91c9601fd%22,%22status%22:0,%22type%22:%222%22%7D%5D,%22users%22:%5B%7B%22type%22:%222%22,%22ids%22:%5B%228a8b71a776e29a320176e5c91c9601fd%22%5D%7D%5D,%22userStr%22:%22%E6%BA%AF%E6%BA%90%E5%8F%96%E8%AF%81%E7%BB%84%22%7D%5D\" camunda:warn=\"%5B%5D\" camunda:usersName=\"%5B%5D\" camunda:dealType=\"1\" camunda:operation=\"3\">\n      <documentation>{\"id\":\"Activity_166ukp1\",\"type\":2,\"des\":\"\",\"users\":[{\"dealUserType\":\"2\",\"users\":[{\"type\":\"2\",\"ids\":[\"8a8b71a776e29a320176e5c91c9601fd\"]}]}],\"waitTime\":\"\",\"waitTimeType\":\"\",\"warn\":[],\"dealType\":\"1\",\"operation\":\"3\"}</documentation>\n      <extensionElements>\n        <camunda:taskListener class=\"com.boot.base.common.util.workflow.TaskCreateListener\" event=\"create\" />\n        <camunda:taskListener class=\"com.boot.base.common.util.workflow.TaskCompleteListener\" event=\"complete\" />\n      </extensionElements>\n      <incoming>Flow_1x0snpy</incoming>\n      <outgoing>Flow_0tki2x7</outgoing>\n    </userTask>\n    <sequenceFlow id=\"Flow_0tki2x7\" name=\"结束\" sourceRef=\"Activity_166ukp1\" targetRef=\"Activity_0acv5io\" camunda:conditions=\"%5B%7B%22and%22:%5B%7B%22field%22:%22reportName%22,%22condition%22:5,%22val%22:%22%22%7D%5D%7D%5D\" camunda:conditionsShows=\"%5B%7B%22and%22:%5B%7B%22fieldName%22:%22%E5%91%8A%E8%AD%A6%E5%90%8D%E7%A7%B0%22,%22conditionName%22:%22%E4%B8%8D%E4%B8%BA%E7%A9%BA%22,%22type%22:%22text%22,%22val%22:%22%22%7D%5D%7D%5D\">\n      <conditionExpression xsi:type=\"tFormalExpression\">${workflowService.expressionBack(\"[{'and':[{'field':'reportName','condition':5,'val':''}]}]\",workOrderId,workOrderObj)}</conditionExpression>\n    </sequenceFlow>\n    <userTask id=\"Activity_0acv5io\" name=\"规则加固\" camunda:candidateUsers=\"${Activity_0acv5io_users}\" camunda:taskType=\"2\" camunda:approvalUsers=\"%5B%7B%22dealUserType%22:%222%22,%22users%22:%5B%7B%22type%22:%222%22,%22ids%22:%5B%228a8b71a776e29a320176f0342cf504d4%22%5D%7D%5D%7D%5D\" camunda:approvalUsersNames=\"%5B%7B%22dealUserTypeNmae%22:%22%E4%BA%BA%E5%91%98,%E9%83%A8%E9%97%A8,%E8%A7%92%E8%89%B2,%E7%94%A8%E6%88%B7%E7%BB%84%22,%22dealUserType%22:%222%22,%22_users%22:%5B%7B%22createTimeFormat%22:%222021-01-11%2014:48:40%22,%22createTime%22:%222021-01-11%2014:48:40%22,%22roleName%22:%22%E8%A7%84%E5%88%99%E4%BA%8B%E4%BB%B6%E7%BB%84%22,%22id%22:%228a8b71a776e29a320176f0342cf504d4%22,%22status%22:0,%22type%22:%222%22%7D%5D,%22users%22:%5B%7B%22type%22:%222%22,%22ids%22:%5B%228a8b71a776e29a320176f0342cf504d4%22%5D%7D%5D,%22userStr%22:%22%E8%A7%84%E5%88%99%E4%BA%8B%E4%BB%B6%E7%BB%84%22%7D%5D\" camunda:warn=\"%5B%5D\" camunda:usersName=\"%5B%5D\" camunda:dealType=\"0\" camunda:fieldsReal=\"%5B%7B%22field%22:%22appendProposal%22,%22name%22:%22%E8%BF%BD%E5%8A%A0%E5%BB%BA%E8%AE%AE%22,%22type%22:%221%22,%22isSelected%22:true%7D%5D\">\n      <documentation>{\"id\":\"Activity_0acv5io\",\"type\":2,\"des\":\"\",\"users\":[{\"dealUserType\":\"2\",\"users\":[{\"type\":\"2\",\"ids\":[\"8a8b71a776e29a320176f0342cf504d4\"]}]}],\"waitTime\":\"\",\"waitTimeType\":\"\",\"warn\":[],\"dealType\":\"0\",\"fields\":[{\"field\":\"appendProposal\",\"name\":\"追加建议\",\"type\":\"1\"}]}</documentation>\n      <extensionElements>\n        <camunda:taskListener class=\"com.boot.base.common.util.workflow.TaskCreateListener\" event=\"create\" />\n        <camunda:taskListener class=\"com.boot.base.common.util.workflow.TaskCompleteListener\" event=\"complete\" />\n      </extensionElements>\n      <incoming>Flow_0tki2x7</incoming>\n      <incoming>Flow_0305dpk</incoming>\n      <outgoing>Flow_0w7v3za</outgoing>\n    </userTask>\n    <endEvent id=\"Event_0zl8d83\" name=\"结束\">\n      <extensionElements>\n        <camunda:executionListener class=\"com.boot.base.common.util.workflow.EndListener\" event=\"end\" />\n      </extensionElements>\n      <incoming>Flow_0w7v3za</incoming>\n      <incoming>Flow_0xuan2g</incoming>\n    </endEvent>\n    <sequenceFlow id=\"Flow_0w7v3za\" name=\"\" sourceRef=\"Activity_0acv5io\" targetRef=\"Event_0zl8d83\">\n      <conditionExpression xsi:type=\"tFormalExpression\">${result==true}</conditionExpression>\n    </sequenceFlow>\n    <exclusiveGateway id=\"Gateway_1590laf\" name=\"分支\">\n      <incoming>Flow_0ef2tb0</incoming>\n      <outgoing>Flow_1x0snpy</outgoing>\n      <outgoing>Flow_0mqarce</outgoing>\n    </exclusiveGateway>\n    <sequenceFlow id=\"Flow_0ef2tb0\" sourceRef=\"Activity_0cptsx9\" targetRef=\"Gateway_1590laf\" />\n    <sequenceFlow id=\"Flow_1x0snpy\" name=\"\" sourceRef=\"Gateway_1590laf\" targetRef=\"Activity_166ukp1\">\n      <conditionExpression xsi:type=\"tFormalExpression\">${result==true}</conditionExpression>\n    </sequenceFlow>\n    <userTask id=\"Activity_0aeichz\" name=\"审批\" camunda:assignee=\"${Activity_0aeichz_per}\" camunda:taskType=\"0\" camunda:approvalUsers=\"%5B%5D\" camunda:approvalUsersNames=\"%5B%5D\" camunda:fieldsReal=\"%5B%5D\" camunda:warn=\"%5B%5D\" camunda:usersName=\"%5B%5D\">\n      <documentation>{\"id\":\"Activity_0aeichz\",\"type\":0,\"des\":\"\",\"fields\":[],\"users\":[],\"waitTime\":\"\",\"waitTimeType\":\"\",\"warn\":[],\"dealType\":2}</documentation>\n      <extensionElements>\n        <camunda:taskListener class=\"com.boot.base.common.util.workflow.TaskCreateListener\" event=\"create\" />\n        <camunda:taskListener class=\"com.boot.base.common.util.workflow.TaskCompleteListener\" event=\"complete\" />\n      </extensionElements>\n      <incoming>Flow_0mqarce</incoming>\n      <outgoing>Flow_0305dpk</outgoing>\n      <outgoing>Flow_0xuan2g</outgoing>\n      <multiInstanceLoopCharacteristics camunda:collection=\"Activity_0aeichz_users\" camunda:elementVariable=\"Activity_0aeichz_per\">\n        <completionCondition>${node_result==true}</completionCondition>\n      </multiInstanceLoopCharacteristics>\n    </userTask>\n    <sequenceFlow id=\"Flow_0305dpk\" name=\"通过\" sourceRef=\"Activity_0aeichz\" targetRef=\"Activity_0acv5io\">\n      <conditionExpression xsi:type=\"tFormalExpression\">${result==true}</conditionExpression>\n    </sequenceFlow>\n    <sequenceFlow id=\"Flow_0mqarce\" name=\"\" sourceRef=\"Gateway_1590laf\" targetRef=\"Activity_0aeichz\">\n      <conditionExpression xsi:type=\"tFormalExpression\">${result==false}</conditionExpression>\n    </sequenceFlow>\n    <userTask id=\"Activity_14bcp30\" name=\"会签\" camunda:assignee=\"${Activity_14bcp30_per}\" camunda:taskType=\"1\" camunda:approvalUsers=\"%5B%5D\" camunda:approvalUsersNames=\"%5B%5D\" camunda:fieldsReal=\"%5B%5D\" camunda:warn=\"%5B%5D\" camunda:usersName=\"%5B%5D\">\n      <documentation>{\"id\":\"Activity_14bcp30\",\"type\":1,\"des\":\"\",\"fields\":[],\"users\":[],\"waitTime\":\"\",\"waitTimeType\":\"\",\"warn\":[],\"dealType\":2}</documentation>\n      <extensionElements>\n        <camunda:taskListener class=\"com.boot.base.common.util.workflow.TaskCreateListener\" event=\"create\" />\n        <camunda:taskListener class=\"com.boot.base.common.util.workflow.TaskCompleteListener\" event=\"complete\" />\n      </extensionElements>\n      <incoming>Flow_0kofjgf</incoming>\n      <outgoing>Flow_1t3iyjh</outgoing>\n      <outgoing>Flow_1dm18qh</outgoing>\n      <multiInstanceLoopCharacteristics camunda:collection=\"Activity_14bcp30_users\" camunda:elementVariable=\"Activity_14bcp30_per\">\n        <completionCondition>${node_result==true}</completionCondition>\n      </multiInstanceLoopCharacteristics>\n    </userTask>\n    <sequenceFlow id=\"Flow_0kofjgf\" name=\"自定义条件\" sourceRef=\"Activity_0cptsx9\" targetRef=\"Activity_14bcp30\" />\n    <serviceTask id=\"Activity_09188ys\" name=\"自动\" camunda:class=\"com.boot.base.common.util.workflow.CallExternalSystemDelegate\" camunda:taskType=\"3\" camunda:warn=\"[]\" camunda:usersName=\"[]\">\n      <documentation>{\"id\":\"Activity_09188ys\",\"type\":3,\"des\":\"\",\"warn\":[]}</documentation>\n      <incoming>Flow_1t3iyjh</incoming>\n      <outgoing>Flow_1gxg525</outgoing>\n    </serviceTask>\n    <sequenceFlow id=\"Flow_1t3iyjh\" name=\"通过\" sourceRef=\"Activity_14bcp30\" targetRef=\"Activity_09188ys\">\n      <conditionExpression xsi:type=\"tFormalExpression\">${result==true}</conditionExpression>\n    </sequenceFlow>\n    <sequenceFlow id=\"Flow_0xuan2g\" name=\"不通过\" sourceRef=\"Activity_0aeichz\" targetRef=\"Event_0zl8d83\">\n      <conditionExpression xsi:type=\"tFormalExpression\">${result==false}</conditionExpression>\n    </sequenceFlow>\n    <parallelGateway id=\"Gateway_1rgfns3\" name=\"并行\">\n      <incoming>Flow_1gxg525</incoming>\n      <outgoing>Flow_1ds6vb7</outgoing>\n      <outgoing>Flow_1iuci8x</outgoing>\n    </parallelGateway>\n    <sequenceFlow id=\"Flow_1gxg525\" sourceRef=\"Activity_09188ys\" targetRef=\"Gateway_1rgfns3\" />\n    <userTask id=\"Activity_0p1edxu\" name=\"处置\" camunda:candidateUsers=\"${Activity_0p1edxu_users}\" camunda:taskType=\"2\" camunda:approvalUsers=\"%5B%5D\" camunda:approvalUsersNames=\"%5B%5D\" camunda:warn=\"%5B%5D\" camunda:usersName=\"%5B%5D\">\n      <documentation>{\"id\":\"Activity_0p1edxu\",\"type\":2,\"des\":\"\",\"users\":[],\"waitTime\":\"\",\"waitTimeType\":\"\",\"warn\":[],\"dealType\":\"\"}</documentation>\n      <extensionElements>\n        <camunda:taskListener class=\"com.boot.base.common.util.workflow.TaskCreateListener\" event=\"create\" />\n        <camunda:taskListener class=\"com.boot.base.common.util.workflow.TaskCompleteListener\" event=\"complete\" />\n      </extensionElements>\n      <incoming>Flow_1ds6vb7</incoming>\n      <incoming>Flow_0efq2sq</incoming>\n      <outgoing>Flow_1y2t5lo</outgoing>\n    </userTask>\n    <userTask id=\"Activity_13x4xn7\" name=\"业务\" camunda:candidateUsers=\"${Activity_13x4xn7_users}\" camunda:taskType=\"2\" camunda:approvalUsers=\"%5B%5D\" camunda:approvalUsersNames=\"%5B%5D\" camunda:warn=\"%5B%5D\" camunda:usersName=\"%5B%5D\">\n      <documentation>{\"id\":\"Activity_13x4xn7\",\"type\":2,\"des\":\"\",\"users\":[],\"waitTime\":\"\",\"waitTimeType\":\"\",\"warn\":[],\"dealType\":\"\"}</documentation>\n      <extensionElements>\n        <camunda:taskListener class=\"com.boot.base.common.util.workflow.TaskCreateListener\" event=\"create\" />\n        <camunda:taskListener class=\"com.boot.base.common.util.workflow.TaskCompleteListener\" event=\"complete\" />\n      </extensionElements>\n      <incoming>Flow_1iuci8x</incoming>\n      <outgoing>Flow_0efq2sq</outgoing>\n    </userTask>\n    <sequenceFlow id=\"Flow_1ds6vb7\" sourceRef=\"Gateway_1rgfns3\" targetRef=\"Activity_0p1edxu\" />\n    <sequenceFlow id=\"Flow_1iuci8x\" sourceRef=\"Gateway_1rgfns3\" targetRef=\"Activity_13x4xn7\" />\n    <endEvent id=\"Event_0ojgw0h\" name=\"结束\">\n      <extensionElements>\n        <camunda:executionListener class=\"com.boot.base.common.util.workflow.EndListener\" event=\"end\" />\n      </extensionElements>\n      <incoming>Flow_1y2t5lo</incoming>\n      <incoming>Flow_1dm18qh</incoming>\n    </endEvent>\n    <sequenceFlow id=\"Flow_1y2t5lo\" sourceRef=\"Activity_0p1edxu\" targetRef=\"Event_0ojgw0h\" />\n    <sequenceFlow id=\"Flow_0efq2sq\" sourceRef=\"Activity_13x4xn7\" targetRef=\"Activity_0p1edxu\" />\n    <sequenceFlow id=\"Flow_1dm18qh\" name=\"不通过\" sourceRef=\"Activity_14bcp30\" targetRef=\"Event_0ojgw0h\" />\n  </process>\n  <bpmndi:BPMNDiagram id=\"BPMNDiagram_flow\">\n    <bpmndi:BPMNPlane id=\"BPMNPlane_flow\" bpmnElement=\"process_1610199116476\">\n      <bpmndi:BPMNEdge id=\"Flow_1dm18qh_di\" bpmnElement=\"Flow_1dm18qh\">\n        <di:waypoint x=\"156\" y=\"160\" />\n        <di:waypoint x=\"-130\" y=\"160\" />\n        <di:waypoint x=\"-130\" y=\"350\" />\n        <bpmndi:BPMNLabel>\n          <omgdc:Bounds x=\"-4\" y=\"142\" width=\"34\" height=\"14\" />\n        </bpmndi:BPMNLabel>\n      </bpmndi:BPMNEdge>\n      <bpmndi:BPMNEdge id=\"Flow_0efq2sq_di\" bpmnElement=\"Flow_0efq2sq\">\n        <di:waypoint x=\"130\" y=\"460\" />\n        <di:waypoint x=\"30\" y=\"460\" />\n        <di:waypoint x=\"30\" y=\"387\" />\n      </bpmndi:BPMNEdge>\n      <bpmndi:BPMNEdge id=\"Flow_1y2t5lo_di\" bpmnElement=\"Flow_1y2t5lo\">\n        <di:waypoint x=\"-20\" y=\"370\" />\n        <di:waypoint x=\"-110\" y=\"370\" />\n      </bpmndi:BPMNEdge>\n      <bpmndi:BPMNEdge id=\"Flow_1iuci8x_di\" bpmnElement=\"Flow_1iuci8x\">\n        <di:waypoint x=\"180\" y=\"394\" />\n        <di:waypoint x=\"180\" y=\"443\" />\n      </bpmndi:BPMNEdge>\n      <bpmndi:BPMNEdge id=\"Flow_1ds6vb7_di\" bpmnElement=\"Flow_1ds6vb7\">\n        <di:waypoint x=\"156\" y=\"370\" />\n        <di:waypoint x=\"80\" y=\"370\" />\n      </bpmndi:BPMNEdge>\n      <bpmndi:BPMNEdge id=\"Flow_1gxg525_di\" bpmnElement=\"Flow_1gxg525\">\n        <di:waypoint x=\"180\" y=\"317\" />\n        <di:waypoint x=\"180\" y=\"346\" />\n      </bpmndi:BPMNEdge>\n      <bpmndi:BPMNEdge id=\"Flow_0xuan2g_di\" bpmnElement=\"Flow_0xuan2g\">\n        <di:waypoint x=\"290\" y=\"184\" />\n        <di:waypoint x=\"290\" y=\"400\" />\n        <di:waypoint x=\"490\" y=\"400\" />\n        <bpmndi:BPMNLabel>\n          <omgdc:Bounds x=\"288\" y=\"289\" width=\"34\" height=\"14\" />\n        </bpmndi:BPMNLabel>\n      </bpmndi:BPMNEdge>\n      <bpmndi:BPMNEdge id=\"Flow_1t3iyjh_di\" bpmnElement=\"Flow_1t3iyjh\">\n        <di:waypoint x=\"180\" y=\"184\" />\n        <di:waypoint x=\"180\" y=\"283\" />\n        <bpmndi:BPMNLabel>\n          <omgdc:Bounds x=\"184\" y=\"231\" width=\"23\" height=\"14\" />\n        </bpmndi:BPMNLabel>\n      </bpmndi:BPMNEdge>\n      <bpmndi:BPMNEdge id=\"Flow_0kofjgf_di\" bpmnElement=\"Flow_0kofjgf\">\n        <di:waypoint x=\"180\" y=\"77\" />\n        <di:waypoint x=\"180\" y=\"136\" />\n        <bpmndi:BPMNLabel>\n          <omgdc:Bounds x=\"167\" y=\"104\" width=\"56\" height=\"14\" />\n        </bpmndi:BPMNLabel>\n      </bpmndi:BPMNEdge>\n      <bpmndi:BPMNEdge id=\"Flow_0mqarce_di\" bpmnElement=\"Flow_0mqarce\">\n        <di:waypoint x=\"290\" y=\"84\" />\n        <di:waypoint x=\"290\" y=\"136\" />\n      </bpmndi:BPMNEdge>\n      <bpmndi:BPMNEdge id=\"Flow_0305dpk_di\" bpmnElement=\"Flow_0305dpk\">\n        <di:waypoint x=\"314\" y=\"160\" />\n        <di:waypoint x=\"480\" y=\"160\" />\n        <di:waypoint x=\"480\" y=\"243\" />\n        <bpmndi:BPMNLabel>\n          <omgdc:Bounds x=\"386\" y=\"142\" width=\"23\" height=\"14\" />\n        </bpmndi:BPMNLabel>\n      </bpmndi:BPMNEdge>\n      <bpmndi:BPMNEdge id=\"Flow_1x0snpy_di\" bpmnElement=\"Flow_1x0snpy\">\n        <di:waypoint x=\"314\" y=\"60\" />\n        <di:waypoint x=\"460\" y=\"60\" />\n      </bpmndi:BPMNEdge>\n      <bpmndi:BPMNEdge id=\"Flow_0ef2tb0_di\" bpmnElement=\"Flow_0ef2tb0\">\n        <di:waypoint x=\"230\" y=\"60\" />\n        <di:waypoint x=\"266\" y=\"60\" />\n      </bpmndi:BPMNEdge>\n      <bpmndi:BPMNEdge id=\"Flow_0w7v3za_di\" bpmnElement=\"Flow_0w7v3za\">\n        <di:waypoint x=\"510\" y=\"277\" />\n        <di:waypoint x=\"510\" y=\"380\" />\n      </bpmndi:BPMNEdge>\n      <bpmndi:BPMNEdge id=\"Flow_0tki2x7_di\" bpmnElement=\"Flow_0tki2x7\">\n        <di:waypoint x=\"510\" y=\"77\" />\n        <di:waypoint x=\"510\" y=\"243\" />\n        <bpmndi:BPMNLabel>\n          <omgdc:Bounds x=\"510\" y=\"118\" width=\"23\" height=\"14\" />\n        </bpmndi:BPMNLabel>\n      </bpmndi:BPMNEdge>\n      <bpmndi:BPMNEdge id=\"Flow_05w48v1_di\" bpmnElement=\"Flow_05w48v1\">\n        <di:waypoint x=\"40\" y=\"60\" />\n        <di:waypoint x=\"130\" y=\"60\" />\n      </bpmndi:BPMNEdge>\n      <bpmndi:BPMNShape id=\"Event_0gly3pi_di\" bpmnElement=\"Event_0gly3pi\">\n        <omgdc:Bounds x=\"0\" y=\"40\" width=\"40\" height=\"40\" />\n        <bpmndi:BPMNLabel>\n          <omgdc:Bounds x=\"10\" y=\"16\" width=\"22\" height=\"14\" />\n        </bpmndi:BPMNLabel>\n      </bpmndi:BPMNShape>\n      <bpmndi:BPMNShape id=\"Activity_0cptsx9_di\" bpmnElement=\"Activity_0cptsx9\">\n        <omgdc:Bounds x=\"130\" y=\"43\" width=\"100\" height=\"34\" />\n      </bpmndi:BPMNShape>\n      <bpmndi:BPMNShape id=\"Activity_166ukp1_di\" bpmnElement=\"Activity_166ukp1\">\n        <omgdc:Bounds x=\"460\" y=\"43\" width=\"100\" height=\"34\" />\n      </bpmndi:BPMNShape>\n      <bpmndi:BPMNShape id=\"Activity_0acv5io_di\" bpmnElement=\"Activity_0acv5io\">\n        <omgdc:Bounds x=\"460\" y=\"243\" width=\"100\" height=\"34\" />\n      </bpmndi:BPMNShape>\n      <bpmndi:BPMNShape id=\"Event_0zl8d83_di\" bpmnElement=\"Event_0zl8d83\">\n        <omgdc:Bounds x=\"490\" y=\"380\" width=\"40\" height=\"40\" />\n        <bpmndi:BPMNLabel>\n          <omgdc:Bounds x=\"499\" y=\"427\" width=\"23\" height=\"14\" />\n        </bpmndi:BPMNLabel>\n      </bpmndi:BPMNShape>\n      <bpmndi:BPMNShape id=\"Gateway_1590laf_di\" bpmnElement=\"Gateway_1590laf\" isMarkerVisible=\"true\">\n        <omgdc:Bounds x=\"266\" y=\"36\" width=\"48\" height=\"48\" />\n        <bpmndi:BPMNLabel>\n          <omgdc:Bounds x=\"278\" y=\"12\" width=\"23\" height=\"14\" />\n        </bpmndi:BPMNLabel>\n      </bpmndi:BPMNShape>\n      <bpmndi:BPMNShape id=\"Activity_0aeichz_di\" bpmnElement=\"Activity_0aeichz\">\n        <omgdc:Bounds x=\"266\" y=\"136\" width=\"48\" height=\"48\" />\n      </bpmndi:BPMNShape>\n      <bpmndi:BPMNShape id=\"Activity_14bcp30_di\" bpmnElement=\"Activity_14bcp30\">\n        <omgdc:Bounds x=\"156\" y=\"136\" width=\"48\" height=\"48\" />\n      </bpmndi:BPMNShape>\n      <bpmndi:BPMNShape id=\"Activity_09188ys_di\" bpmnElement=\"Activity_09188ys\">\n        <omgdc:Bounds x=\"130\" y=\"283\" width=\"100\" height=\"34\" />\n      </bpmndi:BPMNShape>\n      <bpmndi:BPMNShape id=\"Gateway_1rgfns3_di\" bpmnElement=\"Gateway_1rgfns3\">\n        <omgdc:Bounds x=\"156\" y=\"346\" width=\"48\" height=\"48\" />\n        <bpmndi:BPMNLabel>\n          <omgdc:Bounds x=\"213.5\" y=\"363\" width=\"23\" height=\"14\" />\n        </bpmndi:BPMNLabel>\n      </bpmndi:BPMNShape>\n      <bpmndi:BPMNShape id=\"Activity_0p1edxu_di\" bpmnElement=\"Activity_0p1edxu\">\n        <omgdc:Bounds x=\"-20\" y=\"353\" width=\"100\" height=\"34\" />\n      </bpmndi:BPMNShape>\n      <bpmndi:BPMNShape id=\"Activity_13x4xn7_di\" bpmnElement=\"Activity_13x4xn7\">\n        <omgdc:Bounds x=\"130\" y=\"443\" width=\"100\" height=\"34\" />\n      </bpmndi:BPMNShape>\n      <bpmndi:BPMNShape id=\"Event_0ojgw0h_di\" bpmnElement=\"Event_0ojgw0h\">\n        <omgdc:Bounds x=\"-150\" y=\"350\" width=\"40\" height=\"40\" />\n        <bpmndi:BPMNLabel>\n          <omgdc:Bounds x=\"-142\" y=\"393\" width=\"23\" height=\"14\" />\n        </bpmndi:BPMNLabel>\n      </bpmndi:BPMNShape>\n    </bpmndi:BPMNPlane>\n  </bpmndi:BPMNDiagram>\n</definitions>\n",
        "deploymentId": "f91822d1-5b03-11eb-b7a8-02429d5084e0",
        "startConditionObj": [
          {
            "and": [
              {
                "val": "",
                "type": "text",
                "condition": "",
                "field": ""
              }
            ]
          },
          {
            "and": [
              {
                "val": "",
                "type": "text",
                "condition": "",
                "field": ""
              }
            ]
          }
        ],
        "userIds": [
          {
            "name": "管理员",
            "userId": "1"
          },
          {
            "name": "孙广",
            "userId": "ff8080816b3f260e016b3f5389330045"
          },
          {
            "name": "张先生",
            "userId": "402881f16bd05f8f016bd0601b680000"
          },
          {
            "name": "刘欢",
            "userId": "8a8be6ac76e0709d0176ea621d4d0011"
          },
          {
            "name": "张三",
            "userId": "8a8be6ac76b2821b0176dae33ccc02d2"
          },
          {
            "name": "lijing",
            "userId": "8a8be6ac749ff5ed0174b8b89cf30003"
          }
        ],
        "name": "王续专用模板--copy",
        "id": "ff8080817714f7b001771f2d9b350007",
        "status": 1
      },
      {
        "xmlName": "process_1610199116476",
        "createUserId": "8a8be6ac749ff5ed0174b8b89cf30003",
        "sendId": "1",
        "statusCN": "已启动",
        "num": 0,
        "endEventObj": {
          "title": "",
          "type": [],
          "users": [],
          "mes": ""
        },
        "version": 1,
        "createUserCN": "lijing",
        "des": "<p>工单描述</p>",
        "sendCN": "告警",
        "createTime": "2021-01-15 18:49:17",
        "xml": "<?xml version=\"1.0\" encoding=\"UTF-8\"?>\n<definitions xmlns=\"http://www.omg.org/spec/BPMN/20100524/MODEL\" xmlns:xsi=\"http://www.w3.org/2001/XMLSchema-instance\" xmlns:bpmndi=\"http://www.omg.org/spec/BPMN/20100524/DI\" xmlns:omgdc=\"http://www.omg.org/spec/DD/20100524/DC\" xmlns:camunda=\"http://camunda.org/schema/1.0/bpmn\" xmlns:di=\"http://www.omg.org/spec/DD/20100524/DI\" xmlns:xsd=\"http://www.w3.org/2001/XMLSchema\" xmlns:flowable=\"http://flowable.org/bpmn\" targetNamespace=\"http://www.flowable.org/processdef\">\n  <process id=\"process_1610199116476\" name=\"主流程\" isExecutable=\"true\">\n    <startEvent id=\"Event_0gly3pi\" name=\"开始\">\n      <outgoing>Flow_05w48v1</outgoing>\n    </startEvent>\n    <userTask id=\"Activity_0cptsx9\" name=\"分析\" camunda:candidateUsers=\"${Activity_0cptsx9_users}\" camunda:taskType=\"2\" camunda:approvalUsers=\"%5B%7B%22dealUserType%22:%222%22,%22users%22:%5B%7B%22type%22:%222%22,%22ids%22:%5B%224028a7d86b216c9e016b2187b1d70000%22%5D%7D%5D%7D%5D\" camunda:approvalUsersNames=\"%5B%7B%22dealUserTypeNmae%22:%22%E4%BA%BA%E5%91%98,%E9%83%A8%E9%97%A8,%E8%A7%92%E8%89%B2,%E7%94%A8%E6%88%B7%E7%BB%84%22,%22dealUserType%22:%222%22,%22_users%22:%5B%7B%22createTimeFormat%22:%222019-06-04%2016:07:49%22,%22createTime%22:%222019-06-04%2016:07:49%22,%22roleName%22:%22%E5%88%86%E6%9E%90%E7%A0%94%E5%88%A4%E7%BB%84%22,%22id%22:%224028a7d86b216c9e016b2187b1d70000%22,%22status%22:0,%22type%22:%222%22%7D%5D,%22users%22:%5B%7B%22type%22:%222%22,%22ids%22:%5B%224028a7d86b216c9e016b2187b1d70000%22%5D%7D%5D,%22userStr%22:%22%E5%88%86%E6%9E%90%E7%A0%94%E5%88%A4%E7%BB%84%22%7D%5D\" camunda:warn=\"%5B%5D\" camunda:usersName=\"%5B%5D\" camunda:dealType=\"0\" camunda:fieldsReal=\"%5B%7B%22field%22:%22reportName%22,%22name%22:%22%E5%91%8A%E8%AD%A6%E5%90%8D%E7%A7%B0%22,%22type%22:%221%22,%22isSelected%22:true%7D,%7B%22field%22:%22reportLevel%22,%22name%22:%22%E5%91%8A%E8%AD%A6%E7%AD%89%E7%BA%A7%22,%22type%22:%221%22,%22isSelected%22:true%7D,%7B%22field%22:%22analyzePro%22,%22name%22:%22%E5%88%86%E6%9E%90%E8%BF%87%E7%A8%8B%22,%22type%22:%221%22,%22isSelected%22:true%7D,%7B%22field%22:%22disposalAdvise%22,%22name%22:%22%E5%A4%84%E7%BD%AE%E5%BB%BA%E8%AE%AE%22,%22type%22:%221%22,%22isSelected%22:true%7D%5D\">\n      <documentation>{\"id\":\"Activity_0cptsx9\",\"type\":2,\"des\":\"\",\"users\":[{\"dealUserType\":\"2\",\"users\":[{\"type\":\"2\",\"ids\":[\"4028a7d86b216c9e016b2187b1d70000\"]}]}],\"waitTime\":\"\",\"waitTimeType\":\"\",\"warn\":[],\"dealType\":\"0\",\"fields\":[{\"field\":\"reportName\",\"name\":\"告警名称\",\"type\":\"1\"},{\"field\":\"reportLevel\",\"name\":\"告警等级\",\"type\":\"1\"},{\"field\":\"analyzePro\",\"name\":\"分析过程\",\"type\":\"1\"},{\"field\":\"disposalAdvise\",\"name\":\"处置建议\",\"type\":\"1\"}]}</documentation>\n      <extensionElements>\n        <camunda:taskListener class=\"com.boot.base.common.util.workflow.TaskCreateListener\" event=\"create\" />\n        <camunda:taskListener class=\"com.boot.base.common.util.workflow.TaskCompleteListener\" event=\"complete\" />\n      </extensionElements>\n      <incoming>Flow_05w48v1</incoming>\n      <outgoing>Flow_0ef2tb0</outgoing>\n      <outgoing>Flow_0kofjgf</outgoing>\n    </userTask>\n    <sequenceFlow id=\"Flow_05w48v1\" sourceRef=\"Event_0gly3pi\" targetRef=\"Activity_0cptsx9\" />\n    <userTask id=\"Activity_166ukp1\" name=\"溯源\" camunda:candidateUsers=\"${Activity_166ukp1_users}\" camunda:taskType=\"2\" camunda:approvalUsers=\"%5B%7B%22dealUserType%22:%222%22,%22users%22:%5B%7B%22type%22:%222%22,%22ids%22:%5B%228a8b71a776e29a320176e5c91c9601fd%22%5D%7D%5D%7D%5D\" camunda:approvalUsersNames=\"%5B%7B%22dealUserTypeNmae%22:%22%E4%BA%BA%E5%91%98,%E9%83%A8%E9%97%A8,%E8%A7%92%E8%89%B2,%E7%94%A8%E6%88%B7%E7%BB%84%22,%22dealUserType%22:%222%22,%22_users%22:%5B%7B%22createTimeFormat%22:%222021-01-09%2014:15:31%22,%22createTime%22:%222021-01-09%2014:15:31%22,%22roleName%22:%22%E6%BA%AF%E6%BA%90%E5%8F%96%E8%AF%81%E7%BB%84%22,%22id%22:%228a8b71a776e29a320176e5c91c9601fd%22,%22status%22:0,%22type%22:%222%22%7D%5D,%22users%22:%5B%7B%22type%22:%222%22,%22ids%22:%5B%228a8b71a776e29a320176e5c91c9601fd%22%5D%7D%5D,%22userStr%22:%22%E6%BA%AF%E6%BA%90%E5%8F%96%E8%AF%81%E7%BB%84%22%7D%5D\" camunda:warn=\"%5B%5D\" camunda:usersName=\"%5B%5D\" camunda:dealType=\"1\" camunda:operation=\"3\">\n      <documentation>{\"id\":\"Activity_166ukp1\",\"type\":2,\"des\":\"\",\"users\":[{\"dealUserType\":\"2\",\"users\":[{\"type\":\"2\",\"ids\":[\"8a8b71a776e29a320176e5c91c9601fd\"]}]}],\"waitTime\":\"\",\"waitTimeType\":\"\",\"warn\":[],\"dealType\":\"1\",\"operation\":\"3\"}</documentation>\n      <extensionElements>\n        <camunda:taskListener class=\"com.boot.base.common.util.workflow.TaskCreateListener\" event=\"create\" />\n        <camunda:taskListener class=\"com.boot.base.common.util.workflow.TaskCompleteListener\" event=\"complete\" />\n      </extensionElements>\n      <incoming>Flow_1x0snpy</incoming>\n      <outgoing>Flow_0tki2x7</outgoing>\n    </userTask>\n    <sequenceFlow id=\"Flow_0tki2x7\" name=\"结束\" sourceRef=\"Activity_166ukp1\" targetRef=\"Activity_0acv5io\" camunda:conditions=\"%5B%7B%22and%22:%5B%7B%22field%22:%22reportName%22,%22condition%22:5,%22val%22:%22%22%7D%5D%7D%5D\" camunda:conditionsShows=\"%5B%7B%22and%22:%5B%7B%22fieldName%22:%22%E5%91%8A%E8%AD%A6%E5%90%8D%E7%A7%B0%22,%22conditionName%22:%22%E4%B8%8D%E4%B8%BA%E7%A9%BA%22,%22type%22:%22text%22,%22val%22:%22%22%7D%5D%7D%5D\">\n      <conditionExpression xsi:type=\"tFormalExpression\">${workflowService.expressionBack(\"[{'and':[{'field':'reportName','condition':5,'val':''}]}]\",workOrderId,workOrderObj)}</conditionExpression>\n    </sequenceFlow>\n    <userTask id=\"Activity_0acv5io\" name=\"规则加固\" camunda:candidateUsers=\"${Activity_0acv5io_users}\" camunda:taskType=\"2\" camunda:approvalUsers=\"%5B%7B%22dealUserType%22:%222%22,%22users%22:%5B%7B%22type%22:%222%22,%22ids%22:%5B%228a8b71a776e29a320176f0342cf504d4%22%5D%7D%5D%7D%5D\" camunda:approvalUsersNames=\"%5B%7B%22dealUserTypeNmae%22:%22%E4%BA%BA%E5%91%98,%E9%83%A8%E9%97%A8,%E8%A7%92%E8%89%B2,%E7%94%A8%E6%88%B7%E7%BB%84%22,%22dealUserType%22:%222%22,%22_users%22:%5B%7B%22createTimeFormat%22:%222021-01-11%2014:48:40%22,%22createTime%22:%222021-01-11%2014:48:40%22,%22roleName%22:%22%E8%A7%84%E5%88%99%E4%BA%8B%E4%BB%B6%E7%BB%84%22,%22id%22:%228a8b71a776e29a320176f0342cf504d4%22,%22status%22:0,%22type%22:%222%22%7D%5D,%22users%22:%5B%7B%22type%22:%222%22,%22ids%22:%5B%228a8b71a776e29a320176f0342cf504d4%22%5D%7D%5D,%22userStr%22:%22%E8%A7%84%E5%88%99%E4%BA%8B%E4%BB%B6%E7%BB%84%22%7D%5D\" camunda:warn=\"%5B%5D\" camunda:usersName=\"%5B%5D\" camunda:dealType=\"0\" camunda:fieldsReal=\"%5B%7B%22field%22:%22appendProposal%22,%22name%22:%22%E8%BF%BD%E5%8A%A0%E5%BB%BA%E8%AE%AE%22,%22type%22:%221%22,%22isSelected%22:true%7D%5D\">\n      <documentation>{\"id\":\"Activity_0acv5io\",\"type\":2,\"des\":\"\",\"users\":[{\"dealUserType\":\"2\",\"users\":[{\"type\":\"2\",\"ids\":[\"8a8b71a776e29a320176f0342cf504d4\"]}]}],\"waitTime\":\"\",\"waitTimeType\":\"\",\"warn\":[],\"dealType\":\"0\",\"fields\":[{\"field\":\"appendProposal\",\"name\":\"追加建议\",\"type\":\"1\"}]}</documentation>\n      <extensionElements>\n        <camunda:taskListener class=\"com.boot.base.common.util.workflow.TaskCreateListener\" event=\"create\" />\n        <camunda:taskListener class=\"com.boot.base.common.util.workflow.TaskCompleteListener\" event=\"complete\" />\n      </extensionElements>\n      <incoming>Flow_0tki2x7</incoming>\n      <incoming>Flow_0305dpk</incoming>\n      <outgoing>Flow_0w7v3za</outgoing>\n    </userTask>\n    <endEvent id=\"Event_0zl8d83\" name=\"结束\">\n      <extensionElements>\n        <camunda:executionListener class=\"com.boot.base.common.util.workflow.EndListener\" event=\"end\" />\n      </extensionElements>\n      <incoming>Flow_0w7v3za</incoming>\n      <incoming>Flow_0xuan2g</incoming>\n    </endEvent>\n    <sequenceFlow id=\"Flow_0w7v3za\" name=\"\" sourceRef=\"Activity_0acv5io\" targetRef=\"Event_0zl8d83\">\n      <conditionExpression xsi:type=\"tFormalExpression\">${result==true}</conditionExpression>\n    </sequenceFlow>\n    <exclusiveGateway id=\"Gateway_1590laf\" name=\"分支\">\n      <incoming>Flow_0ef2tb0</incoming>\n      <outgoing>Flow_1x0snpy</outgoing>\n      <outgoing>Flow_0mqarce</outgoing>\n    </exclusiveGateway>\n    <sequenceFlow id=\"Flow_0ef2tb0\" sourceRef=\"Activity_0cptsx9\" targetRef=\"Gateway_1590laf\" />\n    <sequenceFlow id=\"Flow_1x0snpy\" name=\"\" sourceRef=\"Gateway_1590laf\" targetRef=\"Activity_166ukp1\">\n      <conditionExpression xsi:type=\"tFormalExpression\">${result==true}</conditionExpression>\n    </sequenceFlow>\n    <userTask id=\"Activity_0aeichz\" name=\"审批\" camunda:assignee=\"${Activity_0aeichz_per}\" camunda:taskType=\"0\" camunda:approvalUsers=\"%5B%5D\" camunda:approvalUsersNames=\"%5B%5D\" camunda:fieldsReal=\"%5B%5D\" camunda:warn=\"%5B%5D\" camunda:usersName=\"%5B%5D\">\n      <documentation>{\"id\":\"Activity_0aeichz\",\"type\":0,\"des\":\"\",\"fields\":[],\"users\":[],\"waitTime\":\"\",\"waitTimeType\":\"\",\"warn\":[],\"dealType\":2}</documentation>\n      <extensionElements>\n        <camunda:taskListener class=\"com.boot.base.common.util.workflow.TaskCreateListener\" event=\"create\" />\n        <camunda:taskListener class=\"com.boot.base.common.util.workflow.TaskCompleteListener\" event=\"complete\" />\n      </extensionElements>\n      <incoming>Flow_0mqarce</incoming>\n      <outgoing>Flow_0305dpk</outgoing>\n      <outgoing>Flow_0xuan2g</outgoing>\n      <multiInstanceLoopCharacteristics camunda:collection=\"Activity_0aeichz_users\" camunda:elementVariable=\"Activity_0aeichz_per\">\n        <completionCondition>${node_result==true}</completionCondition>\n      </multiInstanceLoopCharacteristics>\n    </userTask>\n    <sequenceFlow id=\"Flow_0305dpk\" name=\"通过\" sourceRef=\"Activity_0aeichz\" targetRef=\"Activity_0acv5io\">\n      <conditionExpression xsi:type=\"tFormalExpression\">${result==true}</conditionExpression>\n    </sequenceFlow>\n    <sequenceFlow id=\"Flow_0mqarce\" name=\"\" sourceRef=\"Gateway_1590laf\" targetRef=\"Activity_0aeichz\">\n      <conditionExpression xsi:type=\"tFormalExpression\">${result==false}</conditionExpression>\n    </sequenceFlow>\n    <userTask id=\"Activity_14bcp30\" name=\"会签\" camunda:assignee=\"${Activity_14bcp30_per}\" camunda:taskType=\"1\" camunda:approvalUsers=\"%5B%5D\" camunda:approvalUsersNames=\"%5B%5D\" camunda:fieldsReal=\"%5B%5D\" camunda:warn=\"%5B%5D\" camunda:usersName=\"%5B%5D\">\n      <documentation>{\"id\":\"Activity_14bcp30\",\"type\":1,\"des\":\"\",\"fields\":[],\"users\":[],\"waitTime\":\"\",\"waitTimeType\":\"\",\"warn\":[],\"dealType\":2}</documentation>\n      <extensionElements>\n        <camunda:taskListener class=\"com.boot.base.common.util.workflow.TaskCreateListener\" event=\"create\" />\n        <camunda:taskListener class=\"com.boot.base.common.util.workflow.TaskCompleteListener\" event=\"complete\" />\n      </extensionElements>\n      <incoming>Flow_0kofjgf</incoming>\n      <outgoing>Flow_1t3iyjh</outgoing>\n      <outgoing>Flow_1dm18qh</outgoing>\n      <multiInstanceLoopCharacteristics camunda:collection=\"Activity_14bcp30_users\" camunda:elementVariable=\"Activity_14bcp30_per\">\n        <completionCondition>${node_result==true}</completionCondition>\n      </multiInstanceLoopCharacteristics>\n    </userTask>\n    <sequenceFlow id=\"Flow_0kofjgf\" name=\"自定义条件\" sourceRef=\"Activity_0cptsx9\" targetRef=\"Activity_14bcp30\" />\n    <serviceTask id=\"Activity_09188ys\" name=\"自动\" camunda:class=\"com.boot.base.common.util.workflow.CallExternalSystemDelegate\" camunda:taskType=\"3\" camunda:warn=\"[]\" camunda:usersName=\"[]\">\n      <documentation>{\"id\":\"Activity_09188ys\",\"type\":3,\"des\":\"\",\"warn\":[]}</documentation>\n      <incoming>Flow_1t3iyjh</incoming>\n      <outgoing>Flow_1gxg525</outgoing>\n    </serviceTask>\n    <sequenceFlow id=\"Flow_1t3iyjh\" name=\"通过\" sourceRef=\"Activity_14bcp30\" targetRef=\"Activity_09188ys\">\n      <conditionExpression xsi:type=\"tFormalExpression\">${result==true}</conditionExpression>\n    </sequenceFlow>\n    <sequenceFlow id=\"Flow_0xuan2g\" name=\"不通过\" sourceRef=\"Activity_0aeichz\" targetRef=\"Event_0zl8d83\">\n      <conditionExpression xsi:type=\"tFormalExpression\">${result==false}</conditionExpression>\n    </sequenceFlow>\n    <parallelGateway id=\"Gateway_1rgfns3\" name=\"并行\">\n      <incoming>Flow_1gxg525</incoming>\n      <outgoing>Flow_1ds6vb7</outgoing>\n      <outgoing>Flow_1iuci8x</outgoing>\n    </parallelGateway>\n    <sequenceFlow id=\"Flow_1gxg525\" sourceRef=\"Activity_09188ys\" targetRef=\"Gateway_1rgfns3\" />\n    <userTask id=\"Activity_0p1edxu\" name=\"处置\" camunda:candidateUsers=\"${Activity_0p1edxu_users}\" camunda:taskType=\"2\" camunda:approvalUsers=\"%5B%5D\" camunda:approvalUsersNames=\"%5B%5D\" camunda:warn=\"%5B%5D\" camunda:usersName=\"%5B%5D\">\n      <documentation>{\"id\":\"Activity_0p1edxu\",\"type\":2,\"des\":\"\",\"users\":[],\"waitTime\":\"\",\"waitTimeType\":\"\",\"warn\":[],\"dealType\":\"\"}</documentation>\n      <extensionElements>\n        <camunda:taskListener class=\"com.boot.base.common.util.workflow.TaskCreateListener\" event=\"create\" />\n        <camunda:taskListener class=\"com.boot.base.common.util.workflow.TaskCompleteListener\" event=\"complete\" />\n      </extensionElements>\n      <incoming>Flow_1ds6vb7</incoming>\n      <incoming>Flow_0efq2sq</incoming>\n      <outgoing>Flow_1y2t5lo</outgoing>\n    </userTask>\n    <userTask id=\"Activity_13x4xn7\" name=\"业务\" camunda:candidateUsers=\"${Activity_13x4xn7_users}\" camunda:taskType=\"2\" camunda:approvalUsers=\"%5B%5D\" camunda:approvalUsersNames=\"%5B%5D\" camunda:warn=\"%5B%5D\" camunda:usersName=\"%5B%5D\">\n      <documentation>{\"id\":\"Activity_13x4xn7\",\"type\":2,\"des\":\"\",\"users\":[],\"waitTime\":\"\",\"waitTimeType\":\"\",\"warn\":[],\"dealType\":\"\"}</documentation>\n      <extensionElements>\n        <camunda:taskListener class=\"com.boot.base.common.util.workflow.TaskCreateListener\" event=\"create\" />\n        <camunda:taskListener class=\"com.boot.base.common.util.workflow.TaskCompleteListener\" event=\"complete\" />\n      </extensionElements>\n      <incoming>Flow_1iuci8x</incoming>\n      <outgoing>Flow_0efq2sq</outgoing>\n    </userTask>\n    <sequenceFlow id=\"Flow_1ds6vb7\" sourceRef=\"Gateway_1rgfns3\" targetRef=\"Activity_0p1edxu\" />\n    <sequenceFlow id=\"Flow_1iuci8x\" sourceRef=\"Gateway_1rgfns3\" targetRef=\"Activity_13x4xn7\" />\n    <endEvent id=\"Event_0ojgw0h\" name=\"结束\">\n      <extensionElements>\n        <camunda:executionListener class=\"com.boot.base.common.util.workflow.EndListener\" event=\"end\" />\n      </extensionElements>\n      <incoming>Flow_1y2t5lo</incoming>\n      <incoming>Flow_1dm18qh</incoming>\n    </endEvent>\n    <sequenceFlow id=\"Flow_1y2t5lo\" sourceRef=\"Activity_0p1edxu\" targetRef=\"Event_0ojgw0h\" />\n    <sequenceFlow id=\"Flow_0efq2sq\" sourceRef=\"Activity_13x4xn7\" targetRef=\"Activity_0p1edxu\" />\n    <sequenceFlow id=\"Flow_1dm18qh\" name=\"不通过\" sourceRef=\"Activity_14bcp30\" targetRef=\"Event_0ojgw0h\" />\n  </process>\n  <bpmndi:BPMNDiagram id=\"BPMNDiagram_flow\">\n    <bpmndi:BPMNPlane id=\"BPMNPlane_flow\" bpmnElement=\"process_1610199116476\">\n      <bpmndi:BPMNEdge id=\"Flow_0efq2sq_di\" bpmnElement=\"Flow_0efq2sq\">\n        <di:waypoint x=\"130\" y=\"460\" />\n        <di:waypoint x=\"30\" y=\"460\" />\n        <di:waypoint x=\"30\" y=\"387\" />\n      </bpmndi:BPMNEdge>\n      <bpmndi:BPMNEdge id=\"Flow_1y2t5lo_di\" bpmnElement=\"Flow_1y2t5lo\">\n        <di:waypoint x=\"-20\" y=\"370\" />\n        <di:waypoint x=\"-110\" y=\"370\" />\n      </bpmndi:BPMNEdge>\n      <bpmndi:BPMNEdge id=\"Flow_1iuci8x_di\" bpmnElement=\"Flow_1iuci8x\">\n        <di:waypoint x=\"180\" y=\"394\" />\n        <di:waypoint x=\"180\" y=\"443\" />\n      </bpmndi:BPMNEdge>\n      <bpmndi:BPMNEdge id=\"Flow_1ds6vb7_di\" bpmnElement=\"Flow_1ds6vb7\">\n        <di:waypoint x=\"156\" y=\"370\" />\n        <di:waypoint x=\"80\" y=\"370\" />\n      </bpmndi:BPMNEdge>\n      <bpmndi:BPMNEdge id=\"Flow_1gxg525_di\" bpmnElement=\"Flow_1gxg525\">\n        <di:waypoint x=\"180\" y=\"317\" />\n        <di:waypoint x=\"180\" y=\"346\" />\n      </bpmndi:BPMNEdge>\n      <bpmndi:BPMNEdge id=\"Flow_0xuan2g_di\" bpmnElement=\"Flow_0xuan2g\">\n        <di:waypoint x=\"290\" y=\"184\" />\n        <di:waypoint x=\"290\" y=\"400\" />\n        <di:waypoint x=\"490\" y=\"400\" />\n        <bpmndi:BPMNLabel>\n          <omgdc:Bounds x=\"288\" y=\"289\" width=\"34\" height=\"14\" />\n        </bpmndi:BPMNLabel>\n      </bpmndi:BPMNEdge>\n      <bpmndi:BPMNEdge id=\"Flow_1t3iyjh_di\" bpmnElement=\"Flow_1t3iyjh\">\n        <di:waypoint x=\"180\" y=\"184\" />\n        <di:waypoint x=\"180\" y=\"283\" />\n        <bpmndi:BPMNLabel>\n          <omgdc:Bounds x=\"184\" y=\"231\" width=\"23\" height=\"14\" />\n        </bpmndi:BPMNLabel>\n      </bpmndi:BPMNEdge>\n      <bpmndi:BPMNEdge id=\"Flow_0kofjgf_di\" bpmnElement=\"Flow_0kofjgf\">\n        <di:waypoint x=\"180\" y=\"77\" />\n        <di:waypoint x=\"180\" y=\"136\" />\n        <bpmndi:BPMNLabel>\n          <omgdc:Bounds x=\"167\" y=\"104\" width=\"56\" height=\"14\" />\n        </bpmndi:BPMNLabel>\n      </bpmndi:BPMNEdge>\n      <bpmndi:BPMNEdge id=\"Flow_0mqarce_di\" bpmnElement=\"Flow_0mqarce\">\n        <di:waypoint x=\"290\" y=\"84\" />\n        <di:waypoint x=\"290\" y=\"136\" />\n      </bpmndi:BPMNEdge>\n      <bpmndi:BPMNEdge id=\"Flow_0305dpk_di\" bpmnElement=\"Flow_0305dpk\">\n        <di:waypoint x=\"314\" y=\"160\" />\n        <di:waypoint x=\"480\" y=\"160\" />\n        <di:waypoint x=\"480\" y=\"243\" />\n        <bpmndi:BPMNLabel>\n          <omgdc:Bounds x=\"386\" y=\"142\" width=\"23\" height=\"14\" />\n        </bpmndi:BPMNLabel>\n      </bpmndi:BPMNEdge>\n      <bpmndi:BPMNEdge id=\"Flow_1x0snpy_di\" bpmnElement=\"Flow_1x0snpy\">\n        <di:waypoint x=\"314\" y=\"60\" />\n        <di:waypoint x=\"460\" y=\"60\" />\n      </bpmndi:BPMNEdge>\n      <bpmndi:BPMNEdge id=\"Flow_0ef2tb0_di\" bpmnElement=\"Flow_0ef2tb0\">\n        <di:waypoint x=\"230\" y=\"60\" />\n        <di:waypoint x=\"266\" y=\"60\" />\n      </bpmndi:BPMNEdge>\n      <bpmndi:BPMNEdge id=\"Flow_0w7v3za_di\" bpmnElement=\"Flow_0w7v3za\">\n        <di:waypoint x=\"510\" y=\"277\" />\n        <di:waypoint x=\"510\" y=\"380\" />\n      </bpmndi:BPMNEdge>\n      <bpmndi:BPMNEdge id=\"Flow_0tki2x7_di\" bpmnElement=\"Flow_0tki2x7\">\n        <di:waypoint x=\"510\" y=\"77\" />\n        <di:waypoint x=\"510\" y=\"243\" />\n        <bpmndi:BPMNLabel>\n          <omgdc:Bounds x=\"510\" y=\"118\" width=\"23\" height=\"14\" />\n        </bpmndi:BPMNLabel>\n      </bpmndi:BPMNEdge>\n      <bpmndi:BPMNEdge id=\"Flow_05w48v1_di\" bpmnElement=\"Flow_05w48v1\">\n        <di:waypoint x=\"40\" y=\"60\" />\n        <di:waypoint x=\"130\" y=\"60\" />\n      </bpmndi:BPMNEdge>\n      <bpmndi:BPMNEdge id=\"Flow_1dm18qh_di\" bpmnElement=\"Flow_1dm18qh\">\n        <di:waypoint x=\"156\" y=\"160\" />\n        <di:waypoint x=\"-130\" y=\"160\" />\n        <di:waypoint x=\"-130\" y=\"350\" />\n        <bpmndi:BPMNLabel>\n          <omgdc:Bounds x=\"-4\" y=\"142\" width=\"34\" height=\"14\" />\n        </bpmndi:BPMNLabel>\n      </bpmndi:BPMNEdge>\n      <bpmndi:BPMNShape id=\"Event_0gly3pi_di\" bpmnElement=\"Event_0gly3pi\">\n        <omgdc:Bounds x=\"0\" y=\"40\" width=\"40\" height=\"40\" />\n        <bpmndi:BPMNLabel>\n          <omgdc:Bounds x=\"10\" y=\"16\" width=\"22\" height=\"14\" />\n        </bpmndi:BPMNLabel>\n      </bpmndi:BPMNShape>\n      <bpmndi:BPMNShape id=\"Activity_0cptsx9_di\" bpmnElement=\"Activity_0cptsx9\">\n        <omgdc:Bounds x=\"130\" y=\"43\" width=\"100\" height=\"34\" />\n      </bpmndi:BPMNShape>\n      <bpmndi:BPMNShape id=\"Activity_166ukp1_di\" bpmnElement=\"Activity_166ukp1\">\n        <omgdc:Bounds x=\"460\" y=\"43\" width=\"100\" height=\"34\" />\n      </bpmndi:BPMNShape>\n      <bpmndi:BPMNShape id=\"Activity_0acv5io_di\" bpmnElement=\"Activity_0acv5io\">\n        <omgdc:Bounds x=\"460\" y=\"243\" width=\"100\" height=\"34\" />\n      </bpmndi:BPMNShape>\n      <bpmndi:BPMNShape id=\"Event_0zl8d83_di\" bpmnElement=\"Event_0zl8d83\">\n        <omgdc:Bounds x=\"490\" y=\"380\" width=\"40\" height=\"40\" />\n        <bpmndi:BPMNLabel>\n          <omgdc:Bounds x=\"499\" y=\"427\" width=\"23\" height=\"14\" />\n        </bpmndi:BPMNLabel>\n      </bpmndi:BPMNShape>\n      <bpmndi:BPMNShape id=\"Gateway_1590laf_di\" bpmnElement=\"Gateway_1590laf\" isMarkerVisible=\"true\">\n        <omgdc:Bounds x=\"266\" y=\"36\" width=\"48\" height=\"48\" />\n        <bpmndi:BPMNLabel>\n          <omgdc:Bounds x=\"278\" y=\"12\" width=\"23\" height=\"14\" />\n        </bpmndi:BPMNLabel>\n      </bpmndi:BPMNShape>\n      <bpmndi:BPMNShape id=\"Activity_0aeichz_di\" bpmnElement=\"Activity_0aeichz\">\n        <omgdc:Bounds x=\"266\" y=\"136\" width=\"48\" height=\"48\" />\n      </bpmndi:BPMNShape>\n      <bpmndi:BPMNShape id=\"Activity_14bcp30_di\" bpmnElement=\"Activity_14bcp30\">\n        <omgdc:Bounds x=\"156\" y=\"136\" width=\"48\" height=\"48\" />\n      </bpmndi:BPMNShape>\n      <bpmndi:BPMNShape id=\"Activity_09188ys_di\" bpmnElement=\"Activity_09188ys\">\n        <omgdc:Bounds x=\"130\" y=\"283\" width=\"100\" height=\"34\" />\n      </bpmndi:BPMNShape>\n      <bpmndi:BPMNShape id=\"Gateway_1rgfns3_di\" bpmnElement=\"Gateway_1rgfns3\">\n        <omgdc:Bounds x=\"156\" y=\"346\" width=\"48\" height=\"48\" />\n        <bpmndi:BPMNLabel>\n          <omgdc:Bounds x=\"213.5\" y=\"363\" width=\"23\" height=\"14\" />\n        </bpmndi:BPMNLabel>\n      </bpmndi:BPMNShape>\n      <bpmndi:BPMNShape id=\"Activity_0p1edxu_di\" bpmnElement=\"Activity_0p1edxu\">\n        <omgdc:Bounds x=\"-20\" y=\"353\" width=\"100\" height=\"34\" />\n      </bpmndi:BPMNShape>\n      <bpmndi:BPMNShape id=\"Activity_13x4xn7_di\" bpmnElement=\"Activity_13x4xn7\">\n        <omgdc:Bounds x=\"130\" y=\"443\" width=\"100\" height=\"34\" />\n      </bpmndi:BPMNShape>\n      <bpmndi:BPMNShape id=\"Event_0ojgw0h_di\" bpmnElement=\"Event_0ojgw0h\">\n        <omgdc:Bounds x=\"-150\" y=\"350\" width=\"40\" height=\"40\" />\n        <bpmndi:BPMNLabel>\n          <omgdc:Bounds x=\"-142\" y=\"393\" width=\"23\" height=\"14\" />\n        </bpmndi:BPMNLabel>\n      </bpmndi:BPMNShape>\n    </bpmndi:BPMNPlane>\n  </bpmndi:BPMNDiagram>\n</definitions>\n",
        "deploymentId": "506aeef9-571f-11eb-9d1f-02429d5084e0",
        "startConditionObj": [
          {
            "and": [
              {
                "val": "",
                "type": "text",
                "condition": "",
                "field": ""
              }
            ]
          }
        ],
        "userIds": [
          {
            "name": "管理员",
            "userId": "1"
          },
          {
            "name": "孙广",
            "userId": "ff8080816b3f260e016b3f5389330045"
          },
          {
            "name": "张先生",
            "userId": "402881f16bd05f8f016bd0601b680000"
          },
          {
            "name": "刘欢",
            "userId": "8a8be6ac76e0709d0176ea621d4d0011"
          },
          {
            "name": "张三",
            "userId": "8a8be6ac76b2821b0176dae33ccc02d2"
          },
          {
            "name": "lijing",
            "userId": "8a8be6ac749ff5ed0174b8b89cf30003"
          }
        ],
        "name": "王续专用模板",
        "id": "ff80808176fec641017705a9e742000d",
        "status": 1
      },
      {
        "xmlName": "process_zvjf1f4j",
        "createUserId": "1",
        "sendId": "1",
        "statusCN": "已启动",
        "num": 17,
        "endEventObj": {
          "title": "",
          "type": [],
          "users": [],
          "mes": ""
        },
        "version": 35,
        "createUserCN": "管理员",
        "des": "",
        "sendCN": "告警",
        "createTime": "2021-01-13 16:13:41",
        "xml": "<?xml version=\"1.0\" encoding=\"UTF-8\"?>\n<definitions xmlns=\"http://www.omg.org/spec/BPMN/20100524/MODEL\" xmlns:xsi=\"http://www.w3.org/2001/XMLSchema-instance\" xmlns:bpmndi=\"http://www.omg.org/spec/BPMN/20100524/DI\" xmlns:omgdc=\"http://www.omg.org/spec/DD/20100524/DC\" xmlns:bioc=\"http://bpmn.io/schema/bpmn/biocolor/1.0\" xmlns:camunda=\"http://camunda.org/schema/1.0/bpmn\" xmlns:di=\"http://www.omg.org/spec/DD/20100524/DI\" xmlns:xsd=\"http://www.w3.org/2001/XMLSchema\" xmlns:flowable=\"http://flowable.org/bpmn\" targetNamespace=\"http://www.flowable.org/processdef\">\n  <process id=\"process_zvjf1f4j\" name=\"name_vhcbd31k\" isExecutable=\"true\">\n    <startEvent id=\"startNode1\" name=\"开始\">\n      <outgoing>Flow_1la4uen</outgoing>\n    </startEvent>\n    <userTask id=\"Activity_0v4wzqi\" name=\"分析\" camunda:candidateUsers=\"${Activity_0v4wzqi_users}\" camunda:taskType=\"2\" camunda:approvalUsers=\"%5B%7B%22dealUserType%22:%222%22,%22users%22:%5B%7B%22type%22:%220%22,%22ids%22:%5B%228a8be6ac76e0709d0176ea621d4d0011%22%5D%7D%5D%7D%5D\" camunda:approvalUsersNames=\"%5B%7B%22dealUserTypeNmae%22:%22%E4%BA%BA%E5%91%98,%E9%83%A8%E9%97%A8,%E8%A7%92%E8%89%B2,%E7%94%A8%E6%88%B7%E7%BB%84%22,%22dealUserType%22:%222%22,%22_users%22:%5B%7B%22chineseName%22:%22%E5%88%98%E6%AC%A2%22,%22id%22:%228a8be6ac76e0709d0176ea621d4d0011%22,%22type%22:%220%22%7D%5D,%22users%22:%5B%7B%22type%22:%220%22,%22ids%22:%5B%228a8be6ac76e0709d0176ea621d4d0011%22%5D%7D%5D,%22userStr%22:%22%E5%88%98%E6%AC%A2%22%7D%5D\" camunda:warn=\"%5B%5D\" camunda:usersName=\"%5B%5D\" camunda:des=\"分析的表述\" camunda:dealType=\"1\" camunda:operation=\"0\" camunda:waitTime=\"10\" camunda:waitTimeType=\"1\">\n      <documentation>{\"id\":\"Activity_0v4wzqi\",\"type\":\"2\",\"des\":\"分析的表述\",\"users\":[{\"dealUserType\":\"2\",\"users\":[{\"type\":\"0\",\"ids\":[\"8a8be6ac76e0709d0176ea621d4d0011\"]}]}],\"waitTime\":\"10\",\"waitTimeType\":\"1\",\"warn\":[],\"dealType\":\"1\",\"operation\":\"0\"}</documentation>\n      <extensionElements>\n        <camunda:taskListener class=\"com.boot.base.common.util.workflow.TaskCreateListener\" event=\"create\" />\n        <camunda:taskListener class=\"com.boot.base.common.util.workflow.TaskCompleteListener\" event=\"complete\" />\n      </extensionElements>\n      <incoming>Flow_1la4uen</incoming>\n      <outgoing>Flow_1pd2qeo</outgoing>\n    </userTask>\n    <sequenceFlow id=\"Flow_1la4uen\" sourceRef=\"startNode1\" targetRef=\"Activity_0v4wzqi\" />\n    <userTask id=\"Activity_0fry855\" name=\"溯源\" camunda:candidateUsers=\"${Activity_0fry855_users}\" camunda:taskType=\"2\" camunda:approvalUsers=\"%5B%7B%22dealUserType%22:%222%22,%22users%22:%5B%7B%22type%22:%220%22,%22ids%22:%5B%228a8be6ac76e0709d0176ea621d4d0011%22%5D%7D%5D%7D%5D\" camunda:approvalUsersNames=\"%5B%7B%22dealUserTypeNmae%22:%22%E4%BA%BA%E5%91%98,%E9%83%A8%E9%97%A8,%E8%A7%92%E8%89%B2,%E7%94%A8%E6%88%B7%E7%BB%84%22,%22dealUserType%22:%222%22,%22_users%22:%5B%7B%22chineseName%22:%22%E5%88%98%E6%AC%A2%22,%22id%22:%228a8be6ac76e0709d0176ea621d4d0011%22,%22type%22:%220%22%7D%5D,%22users%22:%5B%7B%22type%22:%220%22,%22ids%22:%5B%228a8be6ac76e0709d0176ea621d4d0011%22%5D%7D%5D,%22userStr%22:%22%E5%88%98%E6%AC%A2%22%7D%5D\" camunda:warn=\"%5B%5D\" camunda:usersName=\"%5B%5D\" camunda:des=\"溯源的描述\" camunda:dealType=\"1\" camunda:operation=\"3\" camunda:waitTime=\"8\" camunda:waitTimeType=\"1\">\n      <documentation>{\"id\":\"Activity_0fry855\",\"type\":\"2\",\"des\":\"溯源的描述\",\"users\":[{\"dealUserType\":\"2\",\"users\":[{\"type\":\"0\",\"ids\":[\"8a8be6ac76e0709d0176ea621d4d0011\"]}]}],\"waitTime\":\"8\",\"waitTimeType\":\"1\",\"warn\":[],\"dealType\":\"1\",\"operation\":\"3\"}</documentation>\n      <extensionElements>\n        <camunda:taskListener class=\"com.boot.base.common.util.workflow.TaskCreateListener\" event=\"create\" />\n        <camunda:taskListener class=\"com.boot.base.common.util.workflow.TaskCompleteListener\" event=\"complete\" />\n      </extensionElements>\n      <incoming>Flow_1pd2qeo</incoming>\n      <outgoing>Flow_0m9o9io</outgoing>\n    </userTask>\n    <sequenceFlow id=\"Flow_1pd2qeo\" sourceRef=\"Activity_0v4wzqi\" targetRef=\"Activity_0fry855\" />\n    <userTask id=\"Activity_1kkszt2\" name=\"处置\" camunda:candidateUsers=\"${Activity_1kkszt2_users}\" camunda:taskType=\"2\" camunda:approvalUsers=\"%5B%7B%22dealUserType%22:%222%22,%22users%22:%5B%7B%22type%22:%220%22,%22ids%22:%5B%228a8be6ac76e0709d0176ea621d4d0011%22%5D%7D%5D%7D%5D\" camunda:approvalUsersNames=\"%5B%7B%22dealUserTypeNmae%22:%22%E4%BA%BA%E5%91%98,%E9%83%A8%E9%97%A8,%E8%A7%92%E8%89%B2,%E7%94%A8%E6%88%B7%E7%BB%84%22,%22dealUserType%22:%222%22,%22_users%22:%5B%7B%22chineseName%22:%22%E5%88%98%E6%AC%A2%22,%22id%22:%228a8be6ac76e0709d0176ea621d4d0011%22,%22type%22:%220%22%7D%5D,%22users%22:%5B%7B%22type%22:%220%22,%22ids%22:%5B%228a8be6ac76e0709d0176ea621d4d0011%22%5D%7D%5D,%22userStr%22:%22%E5%88%98%E6%AC%A2%22%7D%5D\" camunda:warn=\"%5B%5D\" camunda:usersName=\"%5B%5D\" camunda:des=\"处置的描述\" camunda:dealType=\"1\" camunda:operation=\"2\" camunda:waitTime=\"10\" camunda:waitTimeType=\"1\">\n      <documentation>{\"id\":\"Activity_1kkszt2\",\"type\":\"2\",\"des\":\"处置的描述\",\"users\":[{\"dealUserType\":\"2\",\"users\":[{\"type\":\"0\",\"ids\":[\"8a8be6ac76e0709d0176ea621d4d0011\"]}]}],\"waitTime\":\"10\",\"waitTimeType\":\"1\",\"warn\":[],\"dealType\":\"1\",\"operation\":\"2\"}</documentation>\n      <extensionElements>\n        <camunda:taskListener class=\"com.boot.base.common.util.workflow.TaskCreateListener\" event=\"create\" />\n        <camunda:taskListener class=\"com.boot.base.common.util.workflow.TaskCompleteListener\" event=\"complete\" />\n      </extensionElements>\n      <incoming>Flow_0m9o9io</incoming>\n      <outgoing>Flow_0hgtuad</outgoing>\n    </userTask>\n    <sequenceFlow id=\"Flow_0m9o9io\" sourceRef=\"Activity_0fry855\" targetRef=\"Activity_1kkszt2\" />\n    <userTask id=\"Activity_0phbokf\" name=\"编辑字段\" camunda:candidateUsers=\"${Activity_0phbokf_users}\" camunda:taskType=\"2\" camunda:approvalUsers=\"%5B%7B%22dealUserType%22:%222%22,%22users%22:%5B%7B%22type%22:%220%22,%22ids%22:%5B%228a8be6ac76e0709d0176ea621d4d0011%22%5D%7D%5D%7D%5D\" camunda:approvalUsersNames=\"%5B%7B%22dealUserTypeNmae%22:%22%E4%BA%BA%E5%91%98,%E9%83%A8%E9%97%A8,%E8%A7%92%E8%89%B2,%E7%94%A8%E6%88%B7%E7%BB%84%22,%22dealUserType%22:%222%22,%22_users%22:%5B%7B%22chineseName%22:%22%E5%88%98%E6%AC%A2%22,%22id%22:%228a8be6ac76e0709d0176ea621d4d0011%22,%22type%22:%220%22%7D%5D,%22users%22:%5B%7B%22type%22:%220%22,%22ids%22:%5B%228a8be6ac76e0709d0176ea621d4d0011%22%5D%7D%5D,%22userStr%22:%22%E5%88%98%E6%AC%A2%22%7D%5D\" camunda:warn=\"%5B%5D\" camunda:usersName=\"%5B%5D\" camunda:des=\"编辑字段的描述\" camunda:dealType=\"0\" camunda:fieldsReal=\"%5B%7B%22field%22:%22reportName%22,%22name%22:%22%E5%91%8A%E8%AD%A6%E5%90%8D%E7%A7%B0%22,%22type%22:%221%22,%22isSelected%22:true%7D,%7B%22field%22:%22reportLevel%22,%22name%22:%22%E5%91%8A%E8%AD%A6%E7%AD%89%E7%BA%A7%22,%22type%22:%221%22,%22isSelected%22:true%7D,%7B%22field%22:%22attackResult%22,%22name%22:%22%E6%94%BB%E5%87%BB%E7%BB%93%E6%9E%9C%22,%22type%22:%221%22,%22isSelected%22:true%7D,%7B%22field%22:%22reportStatus%22,%22name%22:%22%E5%91%8A%E8%AD%A6%E7%8A%B6%E6%80%81%22,%22type%22:%221%22,%22isSelected%22:true%7D,%7B%22field%22:%22checkStatus%22,%22name%22:%22%E5%AE%A1%E6%A0%B8%E7%8A%B6%E6%80%81%22,%22type%22:%221%22,%22isSelected%22:true%7D,%7B%22field%22:%22isBanned%22,%22name%22:%22%E6%98%AF%E5%90%A6%E5%B0%81%E7%A6%81%22,%22type%22:%221%22,%22isSelected%22:true%7D,%7B%22field%22:%22analyzePro%22,%22name%22:%22%E5%88%86%E6%9E%90%E8%BF%87%E7%A8%8B%22,%22type%22:%221%22,%22isSelected%22:true%7D,%7B%22field%22:%22disposalAdvise%22,%22name%22:%22%E5%A4%84%E7%BD%AE%E5%BB%BA%E8%AE%AE%22,%22type%22:%221%22,%22isSelected%22:true%7D,%7B%22field%22:%22isTrace%22,%22name%22:%22%E6%98%AF%E5%90%A6%E6%BA%AF%E6%BA%90%22,%22type%22:%221%22,%22isSelected%22:true%7D,%7B%22field%22:%22traceResult%22,%22name%22:%22%E6%BA%AF%E6%BA%90%E7%BB%93%E6%9E%9C%22,%22type%22:%221%22,%22isSelected%22:true%7D,%7B%22field%22:%22appendProposal%22,%22name%22:%22%E8%BF%BD%E5%8A%A0%E5%BB%BA%E8%AE%AE%22,%22type%22:%221%22,%22isSelected%22:true%7D%5D\" camunda:waitTime=\"5\" camunda:waitTimeType=\"1\">\n      <documentation>{\"id\":\"Activity_0phbokf\",\"type\":\"2\",\"des\":\"编辑字段的描述\",\"users\":[{\"dealUserType\":\"2\",\"users\":[{\"type\":\"0\",\"ids\":[\"8a8be6ac76e0709d0176ea621d4d0011\"]}]}],\"waitTime\":\"5\",\"waitTimeType\":\"1\",\"warn\":[],\"dealType\":\"0\",\"fields\":[{\"field\":\"reportName\",\"name\":\"告警名称\",\"type\":\"1\"},{\"field\":\"reportLevel\",\"name\":\"告警等级\",\"type\":\"1\"},{\"field\":\"attackResult\",\"name\":\"攻击结果\",\"type\":\"1\"},{\"field\":\"reportStatus\",\"name\":\"告警状态\",\"type\":\"1\"},{\"field\":\"checkStatus\",\"name\":\"审核状态\",\"type\":\"1\"},{\"field\":\"isBanned\",\"name\":\"是否封禁\",\"type\":\"1\"},{\"field\":\"analyzePro\",\"name\":\"分析过程\",\"type\":\"1\"},{\"field\":\"disposalAdvise\",\"name\":\"处置建议\",\"type\":\"1\"},{\"field\":\"isTrace\",\"name\":\"是否溯源\",\"type\":\"1\"},{\"field\":\"traceResult\",\"name\":\"溯源结果\",\"type\":\"1\"},{\"field\":\"appendProposal\",\"name\":\"追加建议\",\"type\":\"1\"}]}</documentation>\n      <extensionElements>\n        <camunda:taskListener class=\"com.boot.base.common.util.workflow.TaskCreateListener\" event=\"create\" />\n        <camunda:taskListener class=\"com.boot.base.common.util.workflow.TaskCompleteListener\" event=\"complete\" />\n      </extensionElements>\n      <incoming>Flow_0hgtuad</incoming>\n      <outgoing>Flow_1cyb176</outgoing>\n    </userTask>\n    <sequenceFlow id=\"Flow_0hgtuad\" sourceRef=\"Activity_1kkszt2\" targetRef=\"Activity_0phbokf\" />\n    <endEvent id=\"Event_0j1l7ps\" name=\"结束\">\n      <extensionElements>\n        <camunda:executionListener class=\"com.boot.base.common.util.workflow.EndListener\" event=\"end\" />\n      </extensionElements>\n      <incoming>Flow_1cyb176</incoming>\n    </endEvent>\n    <sequenceFlow id=\"Flow_1cyb176\" sourceRef=\"Activity_0phbokf\" targetRef=\"Event_0j1l7ps\" />\n  </process>\n  <bpmndi:BPMNDiagram id=\"BPMNDiagram_flow\">\n    <bpmndi:BPMNPlane id=\"BPMNPlane_flow\" bpmnElement=\"process_zvjf1f4j\">\n      <bpmndi:BPMNEdge id=\"Flow_1cyb176_di\" bpmnElement=\"Flow_1cyb176\">\n        <di:waypoint x=\"580\" y=\"-19\" />\n        <di:waypoint x=\"606\" y=\"-20\" />\n        <di:waypoint x=\"606\" y=\"-20\" />\n        <di:waypoint x=\"632\" y=\"-17\" />\n      </bpmndi:BPMNEdge>\n      <bpmndi:BPMNEdge id=\"Flow_0hgtuad_di\" bpmnElement=\"Flow_0hgtuad\">\n        <di:waypoint x=\"430\" y=\"4\" />\n        <di:waypoint x=\"460\" y=\"4\" />\n        <di:waypoint x=\"460\" y=\"-19\" />\n        <di:waypoint x=\"480\" y=\"-19\" />\n      </bpmndi:BPMNEdge>\n      <bpmndi:BPMNEdge id=\"Flow_0m9o9io_di\" bpmnElement=\"Flow_0m9o9io\">\n        <di:waypoint x=\"280\" y=\"27\" />\n        <di:waypoint x=\"310\" y=\"27\" />\n        <di:waypoint x=\"310\" y=\"4\" />\n        <di:waypoint x=\"330\" y=\"4\" />\n      </bpmndi:BPMNEdge>\n      <bpmndi:BPMNEdge id=\"Flow_1pd2qeo_di\" bpmnElement=\"Flow_1pd2qeo\">\n        <di:waypoint x=\"130\" y=\"50\" />\n        <di:waypoint x=\"160\" y=\"50\" />\n        <di:waypoint x=\"160\" y=\"27\" />\n        <di:waypoint x=\"180\" y=\"27\" />\n      </bpmndi:BPMNEdge>\n      <bpmndi:BPMNEdge id=\"Flow_1la4uen_di\" bpmnElement=\"Flow_1la4uen\">\n        <di:waypoint x=\"-20\" y=\"40\" />\n        <di:waypoint x=\"10\" y=\"40\" />\n        <di:waypoint x=\"10\" y=\"50\" />\n        <di:waypoint x=\"30\" y=\"50\" />\n      </bpmndi:BPMNEdge>\n      <bpmndi:BPMNShape id=\"BPMNShape_startNode1\" bpmnElement=\"startNode1\" bioc:stroke=\"\">\n        <omgdc:Bounds x=\"-60\" y=\"20\" width=\"40\" height=\"40\" />\n        <bpmndi:BPMNLabel>\n          <omgdc:Bounds x=\"-57\" y=\"57\" width=\"22\" height=\"14\" />\n        </bpmndi:BPMNLabel>\n      </bpmndi:BPMNShape>\n      <bpmndi:BPMNShape id=\"Activity_0v4wzqi_di\" bpmnElement=\"Activity_0v4wzqi\">\n        <omgdc:Bounds x=\"30\" y=\"33\" width=\"100\" height=\"34\" />\n      </bpmndi:BPMNShape>\n      <bpmndi:BPMNShape id=\"Activity_0fry855_di\" bpmnElement=\"Activity_0fry855\">\n        <omgdc:Bounds x=\"180\" y=\"10\" width=\"100\" height=\"34\" />\n      </bpmndi:BPMNShape>\n      <bpmndi:BPMNShape id=\"Activity_1kkszt2_di\" bpmnElement=\"Activity_1kkszt2\">\n        <omgdc:Bounds x=\"330\" y=\"-13\" width=\"100\" height=\"34\" />\n      </bpmndi:BPMNShape>\n      <bpmndi:BPMNShape id=\"Activity_0phbokf_di\" bpmnElement=\"Activity_0phbokf\">\n        <omgdc:Bounds x=\"480\" y=\"-36\" width=\"100\" height=\"34\" />\n      </bpmndi:BPMNShape>\n      <bpmndi:BPMNShape id=\"Event_0j1l7ps_di\" bpmnElement=\"Event_0j1l7ps\">\n        <omgdc:Bounds x=\"632\" y=\"-37\" width=\"40\" height=\"40\" />\n        <bpmndi:BPMNLabel>\n          <omgdc:Bounds x=\"641\" y=\"10\" width=\"22\" height=\"14\" />\n        </bpmndi:BPMNLabel>\n      </bpmndi:BPMNShape>\n    </bpmndi:BPMNPlane>\n  </bpmndi:BPMNDiagram>\n</definitions>\n",
        "deploymentId": "8f161097-5947-11eb-b7a8-02429d5084e0",
        "startConditionObj": [
          {
            "and": [
              {
                "val": "",
                "type": "text",
                "condition": "",
                "field": ""
              }
            ]
          }
        ],
        "userIds": [
          {
            "name": "管理员",
            "userId": "1"
          },
          {
            "name": "高雁",
            "userId": "8a8be6ac711b790a01711c561968007f"
          },
          {
            "name": "孙广",
            "userId": "ff8080816b3f260e016b3f5389330045"
          },
          {
            "name": "lijing",
            "userId": "8a8be6ac749ff5ed0174b8b89cf30003"
          },
          {
            "name": "刘欢",
            "userId": "8a8be6ac76e0709d0176ea621d4d0011"
          }
        ],
        "name": "多节点模板",
        "id": "ff80808176facae70176faceb5ea0000",
        "status": 1
      }
    ],
    "totalElements": 4
  },
  "code": 1,
  "message": "success"
}